INSTALL.rst
MANIFEST.in
README.rst
VERSION
requirements.txt
setup.cfg
setup.py
tasks.py
src/raining_man/__init__.py
src/raining_man/__main__.py
src/raining_man/__meta__.py
src/raining_man/boy.py
src/raining_man/core.py
src/raining_man/menu.py
src/raining_man/run.py
src/raining_man/shot.py
src/raining_man/world.py
src/raining_man.egg-info/PKG-INFO
src/raining_man.egg-info/SOURCES.txt
src/raining_man.egg-info/dependency_links.txt
src/raining_man.egg-info/entry_points.txt
src/raining_man.egg-info/requires.txt
src/raining_man.egg-info/top_level.txt
src/raining_man/images/1.png
src/raining_man/images/2.png
src/raining_man/images/2parando.png
src/raining_man/images/__init__.py
src/raining_man/images/background.png
src/raining_man/images/firstversion.png
src/raining_man/images/gameover.png
src/raining_man/images/jogar.png
src/raining_man/images/jogar_selecionado.png
src/raining_man/images/menu.png
src/raining_man/images/sair.png
src/raining_man/images/sair_selecionado.png
src/raining_man/images/stone.png
src/raining_man/raining_man/boy.py
src/raining_man/raining_man/run.py
src/raining_man/raining_man/shot.py
src/raining_man/raining_man/world.py
src/raining_man/sounds/__init__.py
src/raining_man/sounds/battle_theme.mp3
src/raining_man/sounds/menu_music.mp3
src/raining_man/sounds/sound-adventure.mp3