Metadata-Version: 1.1
Name: raining-man
Version: 0.1.50
Summary: ITS RAINING MAN!
Home-page: https://github.com/fis-jogos/ep1-rainining-man
Author: Gustavo Lopes de Brito
Author-email: gustavo.ldbrito@gmail.com
License: UNKNOWN
Platform: any
Classifier: Development Status :: 3 - Alpha
Classifier: License :: OSI Approved :: GNU General Public License (GPL)
Classifier: Operating System :: OS Independent
Classifier: Programming Language :: Python
Classifier: Programming Language :: Python :: 3
Classifier: Programming Language :: Python :: 3.4
Classifier: Programming Language :: Python :: 3.5
